client/__init__.py
client/swift_predict.py
services/__init__.py
services/automl_trainer.py
services/preprocessing.py
swiftpredict-0.1.1.dist-info/licenses/LICENSE
swiftpredict-0.1.1.dist-info/METADATA
swiftpredict-0.1.1.dist-info/WHEEL
swiftpredict-0.1.1.dist-info/entry_points.txt
swiftpredict-0.1.1.dist-info/top_level.txt
swiftpredict-0.1.1.dist-info/RECORD
